biobb_godmd/__init__.py
biobb_godmd/py.typed
biobb_godmd/godmd/__init__.py
biobb_godmd/godmd/common.py
biobb_godmd/godmd/godmd_prep.py
biobb_godmd/godmd/godmd_run.py
biobb_godmd-5.2.0.dist-info/licenses/LICENSE
biobb_godmd-5.2.0.dist-info/METADATA
biobb_godmd-5.2.0.dist-info/WHEEL
biobb_godmd-5.2.0.dist-info/entry_points.txt
biobb_godmd-5.2.0.dist-info/top_level.txt
biobb_godmd-5.2.0.dist-info/RECORD
